criclive/__init__.py
criclive/main.py
criclive/tests.py
criclive-0.2.dist-info/LICENSE
criclive-0.2.dist-info/METADATA
criclive-0.2.dist-info/WHEEL
criclive-0.2.dist-info/entry_points.txt
criclive-0.2.dist-info/top_level.txt
criclive-0.2.dist-info/RECORD
